best/__init__.py
best/integration/__init__.py
best/unit/__init__.py
best/unit/conftest.py
best/unit/test_glue_session.py
best/unit/test_glue_session_demo.py
best/unit/test_session_apis.py
drtk-100.0.0.dist-info/LICENSE.txt
drtk-100.0.0.dist-info/METADATA
drtk-100.0.0.dist-info/WHEEL
drtk-100.0.0.dist-info/top_level.txt
drtk-100.0.0.dist-info/RECORD
